HISTORY.rst
LICENSE
MANIFEST.in
README.rst
setup.cfg
setup.py
scrapy_ja3/__init__.py
scrapy_ja3/download_handler.py
scrapy_ja3.egg-info/PKG-INFO
scrapy_ja3.egg-info/SOURCES.txt
scrapy_ja3.egg-info/dependency_links.txt
scrapy_ja3.egg-info/not-zip-safe
scrapy_ja3.egg-info/requires.txt
scrapy_ja3.egg-info/top_level.txt