Metadata-Version: 2.1
Name: scrapy-ja3
Version: 0.1.3
Summary: Scrapy download handler for JA3 fingerprinting
Author: ChenWei Zhao
Author-email: chenwei.zhaozhao@gmail.com
License: MIT
Keywords: scrapy-ja3
Requires-Python: >=3.6
License-File: LICENSE
